webtools.py
revensky.webtools-1.0.0.dist-info/LICENSE
revensky.webtools-1.0.0.dist-info/WHEEL
revensky.webtools-1.0.0.dist-info/METADATA
revensky.webtools-1.0.0.dist-info/RECORD
